[{"url":"https://www.boohooman.com/lace-up-canvas-espadrille/MZZ47121.html","name":"Lace Up Canvas Espadrille","image":"//media.boohooman.com/i/boohooman/mzz47121_navy_xl?$product_image_category_page$","price":"10.50","currency":"GBP"},{"url":"https://www.boohooman.com/lace-up-canvas-espadrille/MZZ47119.html","name":"Lace Up Canvas Espadrille","image":"//media.boohooman.com/i/boohooman/mzz47119_stone_xl?$product_image_category_page$","price":"10.50","currency":"GBP"},{"url":"https://www.boohooman.com/desert-boots/MZZ80787.html","name":"Desert Boots","image":"//media.boohooman.com/i/boohooman/mzz80787_black_xl?$product_image_category_page$","price":"19.60","currency":"GBP"},{"url":"https://www.boohooman.com/man-m-slider/MZZ44432.html","name":"MAN M Slider","image":"//media.boohooman.com/i/boohooman/mzz44432_black_xl?$product_image_category_page$","price":"8.40","currency":"GBP"},{"url":"https://www.boohooman.com/man-dash-sliders/MZZ11194.html","name":"MAN Dash Sliders","image":"//media.boohooman.com/i/boohooman/mzz11194_black_xl?$product_image_category_page$","price":"8.40","currency":"GBP"},{"url":"https://www.boohooman.com/harness-detail-western-boot/MZZ44616.html","name":"Harness Detail Western Boot","image":"//media.boohooman.com/i/boohooman/mzz44616_black_xl?$product_image_category_page$","price":"31.50","currency":"GBP"},{"url":"https://www.boohooman.com/man-dash-sliders/MZZ11196.html","name":"MAN Dash Sliders","image":"//media.boohooman.com/i/boohooman/mzz11196_red_xl?$product_image_category_page$","price":"8.40","currency":"GBP"},{"url":"https://www.boohooman.com/translucent-sole-knitted-trainer/MZZ47135.html","name":"Translucent Sole Knitted Trainer","image":"//media.boohooman.com/i/boohooman/mzz47135_black_xl?$product_image_category_page$","price":"19.60","currency":"GBP"},{"url":"https://www.boohooman.com/translucent-sole-knitted-trainer/MZZ47136.html","name":"Translucent Sole Knitted Trainer","image":"//media.boohooman.com/i/boohooman/mzz47136_white_xl?$product_image_category_page$","price":"19.60","currency":"GBP"},{"url":"https://www.boohooman.com/velvet-panel-chunky-trainer/MZZ11953.html","name":"Velvet Panel Chunky Trainer","image":"//media.boohooman.com/i/boohooman/mzz11953_black_xl?$product_image_category_page$","price":"21.00","currency":"GBP"},{"url":"https://www.boohooman.com/neon-lined-chunky-trainer/MZZ11171.html","name":"Neon Lined Chunky Trainer","image":"//media.boohooman.com/i/boohooman/mzz11171_grey_xl?$product_image_category_page$","price":"21.00","currency":"GBP"},{"url":"https://www.boohooman.com/matte-chunky-trainer/MZZ11164.html","name":"Matte Chunky Trainer","image":"//media.boohooman.com/i/boohooman/mzz11164_black_xl?$product_image_category_page$","price":"21.00","currency":"GBP"},{"url":"https://www.boohooman.com/man-dash-debossed-slider/MZZ44434.html","name":"MAN Dash Debossed Slider","image":"//media.boohooman.com/i/boohooman/mzz44434_white_xl?$product_image_category_page$","price":"8.40","currency":"GBP"},{"url":"https://www.boohooman.com/speckle-sole-chunky-trainer/MZZ47137.html","name":"Speckle Sole Chunky Trainer","image":"//media.boohooman.com/i/boohooman/mzz47137_white_xl?$product_image_category_page$","price":"19.60","currency":"GBP"},{"url":"https://www.boohooman.com/reflective-wave-sole-chunky-trainer/MZZ47138.html","name":"Reflective Wave Sole Chunky Trainer","image":"//media.boohooman.com/i/boohooman/mzz47138_white_xl?$product_image_category_page$","price":"19.60","currency":"GBP"},{"url":"https://www.boohooman.com/man-script-debossed-slider/MZZ44436.html","name":"MAN Script Debossed Slider","image":"//media.boohooman.com/i/boohooman/mzz44436_black_xl?$product_image_category_page$","price":"8.40","currency":"GBP"},{"url":"https://www.boohooman.com/reflective-wave-sole-chunky-trainer/MZZ47140.html","name":"Reflective Wave Sole Chunky Trainer","image":"//media.boohooman.com/i/boohooman/mzz47140_black_xl?$product_image_category_page$","price":"19.60","currency":"GBP"},{"url":"https://www.boohooman.com/man-script-debossed-slider/MZZ44435.html","name":"MAN Script Debossed Slider","image":"//media.boohooman.com/i/boohooman/mzz44435_white_xl?$product_image_category_page$","price":"8.40","currency":"GBP"},{"url":"https://www.boohooman.com/reflective-wave-sole-chunky-trainer/MZZ47139.html","name":"Reflective Wave Sole Chunky Trainer","image":"//media.boohooman.com/i/boohooman/mzz47139_grey_xl?$product_image_category_page$","price":"19.60","currency":"GBP"},{"url":"https://www.boohooman.com/man-script-stripe-slider/MZZ44431.html","name":"MAN Script Stripe Slider","image":"//media.boohooman.com/i/boohooman/mzz44431_black_xl?$product_image_category_page$","price":"8.40","currency":"GBP"},{"url":"https://www.boohooman.com/party-sequin-loafers/MZZ30463.html","name":"Party Sequin Loafers","image":"//media.boohooman.com/i/boohooman/mzz30463_silver_xl?$product_image_category_page$","price":"24.50","currency":"GBP"},{"url":"https://www.boohooman.com/man-script-slider/MZZ11167.html","name":"MAN Script Slider","image":"//media.boohooman.com/i/boohooman/mzz11167_red_xl?$product_image_category_page$","price":"8.40","currency":"GBP"},{"url":"https://www.boohooman.com/man-script-sliders/MZZ11165.html","name":"MAN Script Sliders","image":"//media.boohooman.com/i/boohooman/mzz11165_black_xl?$product_image_category_page$","price":"8.40","currency":"GBP"},{"url":"https://www.boohooman.com/velvet-side-tape-trainers/MZZ11170.html","name":"Velvet Side Tape Trainers","image":"//media.boohooman.com/i/boohooman/mzz11170_navy_xl?$product_image_category_page$","price":"17.50","currency":"GBP"},{"url":"https://www.boohooman.com/contrast-velvet-side-tape-trainer/MZZ11952.html","name":"Contrast Velvet Side Tape Trainer","image":"//media.boohooman.com/i/boohooman/mzz11952_black_xl?$product_image_category_page$","price":"17.50","currency":"GBP"},{"url":"https://www.boohooman.com/man-script-slider/MZZ11166.html","name":"MAN Script Slider","image":"//media.boohooman.com/i/boohooman/mzz11166_white_xl?$product_image_category_page$","price":"8.40","currency":"GBP"},{"url":"https://www.boohooman.com/velvet-side-tape-trainer/MZZ11168.html","name":"Velvet Side Tape Trainer","image":"//media.boohooman.com/i/boohooman/mzz11168_burgundy_xl?$product_image_category_page$","price":"17.50","currency":"GBP"},{"url":"https://www.boohooman.com/party-sequin-loafers/MZZ40463.html","name":"Party Sequin Loafers","image":"//media.boohooman.com/i/boohooman/mzz40463_gold_xl?$product_image_category_page$","price":"24.50","currency":"GBP"},{"url":"https://www.boohooman.com/imitation-suede-western-boot/MZZ44613.html","name":"Imitation Suede Western Boot","image":"//media.boohooman.com/i/boohooman/mzz44613_tan_xl?$product_image_category_page$","price":"17.50","currency":"GBP"},{"url":"https://www.boohooman.com/imitation-suede-western-boot/MZZ44614.html","name":"Imitation Suede Western Boot","image":"//media.boohooman.com/i/boohooman/mzz44614_black_xl?$product_image_category_page$","price":"24.50","currency":"GBP"},{"url":"https://www.boohooman.com/buckle-wrap-around-chelsea-boot/MZZ11162.html","name":"Buckle Wrap Around Chelsea Boot","image":"//media.boohooman.com/i/boohooman/mzz11162_black_xl?$product_image_category_page$","price":"12.50","currency":"GBP"},{"url":"https://www.boohooman.com/man-tab-chunky-trainer/MZZ42076.html","name":"MAN Tab Chunky Trainer","image":"//media.boohooman.com/i/boohooman/mzz42076_black_xl?$product_image_category_page$","price":"17.50","currency":"GBP"},{"url":"https://www.boohooman.com/leather-look-brogue-shoes/MZZ40455.html","name":"Leather Look Brogue Shoes","image":"//media.boohooman.com/i/boohooman/mzz40455_black_xl?$product_image_category_page$","price":"17.50","currency":"GBP"},{"url":"https://www.boohooman.com/smart-faux-suede-brogue-shoes/MZZ40454.html","name":"Smart Faux Suede Brogue Shoes","image":"//media.boohooman.com/i/boohooman/mzz40454_black_xl?$product_image_category_page$","price":"17.50","currency":"GBP"},{"url":"https://www.boohooman.com/bhm1-print-slider/MZZ44438.html","name":"BHM1 Print Slider","image":"//media.boohooman.com/i/boohooman/mzz44438_white_xl?$product_image_category_page$","price":"5.60","currency":"GBP"},{"url":"https://www.boohooman.com/faux-suede-smart-shoes/MZZ40460.html","name":"Faux Suede Smart Shoes","image":"//media.boohooman.com/i/boohooman/mzz40460_black_xl?$product_image_category_page$","price":"17.50","currency":"GBP"},{"url":"https://www.boohooman.com/man-stripe-slider/MZZ44441.html","name":"MAN Stripe Slider","image":"//media.boohooman.com/i/boohooman/mzz44441_white_xl?$product_image_category_page$","price":"8.40","currency":"GBP"},{"url":"https://www.boohooman.com/man.-print-slider/MZZ44440.html","name":"MAN. Print Slider","image":"//media.boohooman.com/i/boohooman/mzz44440_black_xl?$product_image_category_page$","price":"8.40","currency":"GBP"},{"url":"https://www.boohooman.com/silver-side-tape-trainer/MZZ43015.html","name":"Silver Side Tape Trainer","image":"//media.boohooman.com/i/boohooman/mzz43015_white_xl?$product_image_category_page$","price":"17.50","currency":"GBP"},{"url":"https://www.boohooman.com/faux-suede-chelsea-boots/MZZ42288.html","name":"Faux Suede Chelsea Boots","image":"//media.boohooman.com/i/boohooman/mzz42288_tan_xl?$product_image_category_page$","price":"19.60","currency":"GBP"},{"url":"https://www.boohooman.com/faux-suede-chelsea-boots/MZZ42289.html","name":"Faux Suede Chelsea Boots","image":"//media.boohooman.com/i/boohooman/mzz42289_black_xl?$product_image_category_page$","price":"14.00","currency":"GBP"},{"url":"https://www.boohooman.com/camo-worker-boots/MZZ11080.html","name":"Camo Worker Boots","image":"//media.boohooman.com/i/boohooman/mzz11080_camo_xl?$product_image_category_page$","price":"12.50","currency":"GBP"},{"url":"https://www.boohooman.com/man-mmxiii-print-slider/MZZ44437.html","name":"MAN MMXIII Print Slider","image":"//media.boohooman.com/i/boohooman/mzz44437_black_xl?$product_image_category_page$","price":"8.40","currency":"GBP"},{"url":"https://www.boohooman.com/man.-print-slider/MZZ44439.html","name":"MAN. Print Slider","image":"//media.boohooman.com/i/boohooman/mzz44439_white_xl?$product_image_category_page$","price":"8.40","currency":"GBP"},{"url":"https://www.boohooman.com/man-stripe-slider/MZZ44442.html","name":"MAN Stripe Slider","image":"//media.boohooman.com/i/boohooman/mzz44442_black_xl?$product_image_category_page$","price":"8.40","currency":"GBP"},{"url":"https://www.boohooman.com/worker-boots/MZZ11082.html","name":"Worker Boots","image":"//media.boohooman.com/i/boohooman/mzz11082_slate_xl?$product_image_category_page$","price":"12.50","currency":"GBP"},{"url":"https://www.boohooman.com/worker-boots/MZZ11083.html","name":"Worker Boots","image":"//media.boohooman.com/i/boohooman/mzz11083_taupe_xl?$product_image_category_page$","price":"12.50","currency":"GBP"},{"url":"https://www.boohooman.com/matte-black-chunky-trainer/MZZ42170.html","name":"Matte Black Chunky Trainer","image":"//media.boohooman.com/i/boohooman/mzz42170_black_xl?$product_image_category_page$","price":"21.00","currency":"GBP"},{"url":"https://www.boohooman.com/faux-suede-chelsea-boots/MZZ42287.html","name":"Faux Suede Chelsea Boots","image":"//media.boohooman.com/i/boohooman/mzz42287_grey_xl?$product_image_category_page$","price":"19.60","currency":"GBP"},{"url":"https://www.boohooman.com/leather-look-brogues-with-contrast-stitch/MZZ40457.html","name":"Leather Look Brogues With Contrast Stitch","image":"//media.boohooman.com/i/boohooman/mzz40457_black_xl?$product_image_category_page$","price":"14.00","currency":"GBP"},{"url":"https://www.boohooman.com/leather-look-brogue-shoes/MZZ40456.html","name":"Leather Look Brogue Shoes","image":"//media.boohooman.com/i/boohooman/mzz40456_black_xl?$product_image_category_page$","price":"14.00","currency":"GBP"},{"url":"https://www.boohooman.com/croc-trainers-with-side-tape/MZZ40472.html","name":"Croc Trainers With Side Tape","image":"//media.boohooman.com/i/boohooman/mzz40472_black_xl?$product_image_category_page$","price":"17.50","currency":"GBP"},{"url":"https://www.boohooman.com/lace-up-texture-trainers/MZZ40470.html","name":"Lace Up Texture Trainers","image":"//media.boohooman.com/i/boohooman/mzz40470_black_xl?$product_image_category_page$","price":"12.60","currency":"GBP"},{"url":"https://www.boohooman.com/mono-colour-chunky-trainer/MZZ43016.html","name":"Mono Colour Chunky Trainer","image":"//media.boohooman.com/i/boohooman/mzz43016_black_xl?$product_image_category_page$","price":"21.00","currency":"GBP"},{"url":"https://www.boohooman.com/leather-look-chelsea-boots/MZZ11077.html","name":"Leather Look Chelsea Boots","image":"//media.boohooman.com/i/boohooman/mzz11077_black_xl?$product_image_category_page$","price":"15.00","currency":"GBP"},{"url":"https://www.boohooman.com/faux-leather-brogue-shoes/MZZ40458.html","name":"Faux Leather Brogue Shoes","image":"//media.boohooman.com/i/boohooman/mzz40458_black_xl?$product_image_category_page$","price":"17.50","currency":"GBP"},{"url":"https://www.boohooman.com/worker-boots/MZZ11084.html","name":"Worker Boots","image":"//media.boohooman.com/i/boohooman/mzz11084_tan_xl?$product_image_category_page$","price":"12.50","currency":"GBP"},{"url":"https://www.boohooman.com/colour-block-panel-trainer/MZZ40465.html","name":"Colour Block Panel Trainer","image":"//media.boohooman.com/i/boohooman/mzz40465_red_xl?$product_image_category_page$","price":"17.50","currency":"GBP"},{"url":"https://www.boohooman.com/leather-look-chelsea-boots/MZZ11078.html","name":"Leather Look Chelsea Boots","image":"//media.boohooman.com/i/boohooman/mzz11078_brown_xl?$product_image_category_page$","price":"15.00","currency":"GBP"},{"url":"https://www.boohooman.com/smart-velvet-shoes/MZZ11079.html","name":"Smart Velvet Shoes","image":"//media.boohooman.com/i/boohooman/mzz11079_black_xl?$product_image_category_page$","price":"21.00","currency":"GBP"},{"url":"https://www.boohooman.com/colour-block-panel-trainer/MZZ40466.html","name":"Colour Block Panel Trainer","image":"//media.boohooman.com/i/boohooman/mzz40466_black_xl?$product_image_category_page$","price":"17.50","currency":"GBP"},{"url":"https://www.boohooman.com/croc-lace-up-trainers/MZZ40471.html","name":"Croc Lace Up Trainers","image":"//media.boohooman.com/i/boohooman/mzz40471_black_xl?$product_image_category_page$","price":"17.50","currency":"GBP"},{"url":"https://www.boohooman.com/leather-look-loafers/MZZ40461.html","name":"Leather Look Loafers","image":"//media.boohooman.com/i/boohooman/mzz40461_black_xl?$product_image_category_page$","price":"17.50","currency":"GBP"},{"url":"https://www.boohooman.com/side-tape-detail-trainer/MZZ47662.html","name":"Side Tape Detail Trainer","image":"//media.boohooman.com/i/boohooman/mzz47662_navy_xl?$product_image_category_page$","price":"17.50","currency":"GBP"},{"url":"https://www.boohooman.com/multi-panel-neon-chunky-trainer/MZZ38413.html","name":"Multi Panel Neon Chunky Trainer","image":"//media.boohooman.com/i/boohooman/mzz38413_multi_xl?$product_image_category_page$","price":"11.00","currency":"GBP"},{"url":"https://www.boohooman.com/neon-side-tape-detail-trainer/MZZ45538.html","name":"Neon Side Tape Detail Trainer","image":"//media.boohooman.com/i/boohooman/mzz45538_white_xl?$product_image_category_page$","price":"12.00","currency":"GBP"},{"url":"https://www.boohooman.com/side-tape-detail-trainer/MZZ48752.html","name":"Side Tape Detail Trainer","image":"//media.boohooman.com/i/boohooman/mzz48752_black_xl?$product_image_category_page$","price":"17.50","currency":"GBP"},{"url":"https://www.boohooman.com/man-printed-chunky-trainers/MZZ38412.html","name":"MAN Printed Chunky Trainers","image":"//media.boohooman.com/i/boohooman/mzz38412_white_xl?$product_image_category_page$","price":"17.50","currency":"GBP"},{"url":"https://www.boohooman.com/extended-sole-chunky-trainer/MZZ38420.html","name":"Extended Sole Chunky Trainer","image":"//media.boohooman.com/i/boohooman/mzz38420_white_xl?$product_image_category_page$","price":"18.20","currency":"GBP"},{"url":"https://www.boohooman.com/chunky-trainers-with-plastic-tab/MZZ38415.html","name":"Chunky Trainers With Plastic Tab","image":"//media.boohooman.com/i/boohooman/mzz38415_white_xl?$product_image_category_page$","price":"21.00","currency":"GBP"},{"url":"https://www.boohooman.com/side-tape-detail-trainer/MZZ45540.html","name":"Side Tape Detail Trainer","image":"//media.boohooman.com/i/boohooman/mzz45540_grey_xl?$product_image_category_page$","price":"17.50","currency":"GBP"},{"url":"https://www.boohooman.com/neon-lining-chunky-trainer/MZZ48760.html","name":"Neon Lining Chunky Trainer","image":"//media.boohooman.com/i/boohooman/mzz48760_white_xl?$product_image_category_page$","price":"15.40","currency":"GBP"},{"url":"https://www.boohooman.com/multi-panel-chunky-trainer-with-man-tape/MZZ51906.html","name":"Multi Panel Chunky Trainer With MAN Tape","image":"//media.boohooman.com/i/boohooman/mzz51906_white_xl?$product_image_category_page$","price":"21.00","currency":"GBP"},{"url":"https://www.boohooman.com/snake-side-tape-trainer/MZZ45542.html","name":"Snake Side Tape Trainer","image":"//media.boohooman.com/i/boohooman/mzz45542_white_xl?$product_image_category_page$","price":"17.50","currency":"GBP"},{"url":"https://www.boohooman.com/side-tape-detail-trainer/MZZ45539.html","name":"Side Tape Detail Trainer","image":"//media.boohooman.com/i/boohooman/mzz45539_stone_xl?$product_image_category_page$","price":"17.50","currency":"GBP"},{"url":"https://www.boohooman.com/knitted-sock-man-trainer/MZZ51423.html","name":"Knitted Sock MAN Trainer","image":"//media.boohooman.com/i/boohooman/mzz51423_sand_xl?$product_image_category_page$","price":"21.00","currency":"GBP"},{"url":"https://www.boohooman.com/faux-suede-metal-snaffle-loafer/MZZ53930.html","name":"Faux Suede Metal Snaffle Loafer","image":"//media.boohooman.com/i/boohooman/mzz53930_tan_xl?$product_image_category_page$","price":"17.50","currency":"GBP"},{"url":"https://www.boohooman.com/stripe-slider/MZZ47040.html","name":"Stripe Slider","image":"//media.boohooman.com/i/boohooman/mzz47040_white_xl?$product_image_category_page$","price":"7.00","currency":"GBP"},{"url":"https://www.boohooman.com/aqua-panel-chunky-trainer/MZZ45536.html","name":"Aqua Panel Chunky Trainer","image":"//media.boohooman.com/i/boohooman/mzz45536_black_xl?$product_image_category_page$","price":"21.00","currency":"GBP"},{"url":"https://www.boohooman.com/contrast-panel-bubble-sole-mesh-chunky-trainer/MZZ56381.html","name":"Contrast Panel Bubble Sole Mesh Chunky Trainer","image":"//media.boohooman.com/i/boohooman/mzz56381_red_xl?$product_image_category_page$","price":"19.60","currency":"GBP"}]